pk_regression-0.0.2.dist-info/licenses/LICENSE
pkr/__init__.py
pkr/cli.py
pkr/pkr.py
pk_regression-0.0.2.dist-info/METADATA
pk_regression-0.0.2.dist-info/WHEEL
pk_regression-0.0.2.dist-info/entry_points.txt
pk_regression-0.0.2.dist-info/top_level.txt
pk_regression-0.0.2.dist-info/RECORD
