Metadata-Version: 2.4
Name: pk-regression
Version: 0.0.2
Summary: Pure Kernel Regression: noise-free, explainable tabular regression via high-purity feature windows
Home-page: https://github.com/YusufBurak/PKR
Author: Yusuf Burak
Author-email: your.email@example.com
License: MIT
Classifier: Development Status :: 4 - Beta
Classifier: Programming Language :: Python :: 3
Classifier: License :: OSI Approved :: MIT License
Classifier: Intended Audience :: Science/Research
Classifier: Topic :: Scientific/Engineering :: Artificial Intelligence
Requires-Python: >=3.8
License-File: LICENSE
Requires-Dist: numpy>=1.21
Requires-Dist: pandas>=1.4
Requires-Dist: joblib>=1.3
Dynamic: license-file
